README.rst
microarray_quantilenorm
setup.py
microarray_quantilenorm/__init__.py
microarray_quantilenorm/microarray_quantilenorm.py
microarray_quantilenorm/mq.py
microarray_quantilenorm.egg-info/PKG-INFO
microarray_quantilenorm.egg-info/SOURCES.txt
microarray_quantilenorm.egg-info/dependency_links.txt
microarray_quantilenorm.egg-info/requires.txt
microarray_quantilenorm.egg-info/top_level.txt