Metadata-Version: 1.1
Name: microarray-quantilenorm
Version: 0.1008
Summary: Quantile normalization of microarray data.
Home-page: http://github.com/githubuser8392/microarray-quantilenorm/
Author: githubuser8392
Author-email: pypi@account.neomailbox.ch
License: GNU General Public License v2
Platform: any
Classifier: Programming Language :: Python
Classifier: Development Status :: 4 - Beta
Classifier: Natural Language :: English
Classifier: Environment :: Console
Classifier: Intended Audience :: Developers
Classifier: License :: OSI Approved :: GNU General Public License v2 (GPLv2)
Classifier: Operating System :: OS Independent
Classifier: Topic :: Software Development :: Libraries :: Python Modules
